django_robots_and_sitemap-1.0.2.dist-info/licenses/LICENSE
robots_and_sitemap/__init__.py
robots_and_sitemap/apps.py
robots_and_sitemap/decorators.py
robots_and_sitemap/urls.py
robots_and_sitemap/views.py
django_robots_and_sitemap-1.0.2.dist-info/METADATA
django_robots_and_sitemap-1.0.2.dist-info/WHEEL
django_robots_and_sitemap-1.0.2.dist-info/top_level.txt
django_robots_and_sitemap-1.0.2.dist-info/RECORD
